MANIFEST.in
README.md
setup.py
pretty/__init__.py
pretty/code_pretty_extension.py
python_markdown_pretty.egg-info/PKG-INFO
python_markdown_pretty.egg-info/SOURCES.txt
python_markdown_pretty.egg-info/dependency_links.txt
python_markdown_pretty.egg-info/not-zip-safe
python_markdown_pretty.egg-info/requires.txt
python_markdown_pretty.egg-info/top_level.txt