Metadata-Version: 1.1
Name: python-markdown-pretty
Version: 1.0.1
Summary: Code pretty  extension for python-markdown
Home-page: https://github.com/joywek/python-markdown-pretty
Author: Joywek
Author-email: joywek@gmail.com
License: BSD License
Keywords: markdown pygments
Platform: UNKNOWN
Classifier: Programming Language :: Python
Classifier: Development Status :: 4 - Beta
Classifier: Environment :: Plugins
Classifier: Intended Audience :: Developers
Classifier: License :: OSI Approved :: MIT License
Classifier: Operating System :: OS Independent
Classifier: Topic :: Software Development :: Libraries :: Python Modules
Classifier: Topic :: Text Processing :: Markup
